mirai_onebot/__init__.py
mirai_onebot/adapters/__init__.py
mirai_onebot/adapters/base.py
mirai_onebot/adapters/reverse_websocket_adapter.py
mirai_onebot/api/__init__.py
mirai_onebot/api/api_provider.py
mirai_onebot/api/interfaces/__init__.py
mirai_onebot/api/interfaces/base.py
mirai_onebot/api/interfaces/group.py
mirai_onebot/api/interfaces/message.py
mirai_onebot/api/interfaces/meta.py
mirai_onebot/bot.py
mirai_onebot/event/__init__.py
mirai_onebot/event/bus.py
mirai_onebot/event/event_base.py
mirai_onebot/event/group_event.py
mirai_onebot/event/private_direct_event.py
mirai_onebot/message/__init__.py
mirai_onebot/message/message_chain.py
mirai_onebot/message/message_components.py
mirai_onebot/utils/__init__.py
yiri_mirai_onebot-0.0.1.dist-info/LICENSE
yiri_mirai_onebot-0.0.1.dist-info/METADATA
yiri_mirai_onebot-0.0.1.dist-info/WHEEL
yiri_mirai_onebot-0.0.1.dist-info/RECORD
