Metadata-Version: 2.1
Name: yiri-mirai-onebot
Version: 0.0.1
Summary: YiriMiraiOneBot是一个OneBot 12协议上的Python SDK，延续YiriMirai项目轻量级、低耦合的编码风格。
Home-page: https://github.com/YiriMiraiProject/YiriMiraiOneBot
License: AGPL-3.0
Author: XYCode Kerman
Author-email: xycode-xyc@outlook.com
Requires-Python: >=3.8
Classifier: Development Status :: 3 - Alpha
Classifier: Framework :: AsyncIO
Classifier: Intended Audience :: Developers
Classifier: License :: OSI Approved :: GNU Affero General Public License v3
Classifier: License :: OSI Approved :: GNU Lesser General Public License v3 (LGPLv3)
Classifier: Programming Language :: Python :: 3
Classifier: Programming Language :: Python :: 3.8
Classifier: Programming Language :: Python :: 3.9
Classifier: Programming Language :: Python :: 3.10
Classifier: Programming Language :: Python :: 3.11
Classifier: Programming Language :: Python :: 3.12
Classifier: Programming Language :: Python :: 3 :: Only
Classifier: Programming Language :: Python :: 3.13
Classifier: Programming Language :: Python :: 3.14
Classifier: Topic :: Communications
Requires-Dist: objprint (>=0.2.3,<0.3.0)
Requires-Dist: pydantic (>=2.7.4,<3.0.0)
Requires-Dist: rich (>=13.7.0,<14.0.0)
Requires-Dist: websockets (>=12.0,<13.0)
Project-URL: Repository, https://github.com/YiriMiraiProject/YiriMiraiOneBot
